[
    
    {
      "name": "Olarewaju Family",
      "members": 4,
      "methodOfInvitation": "Phone"   
    },
    {
        "name": "Akpan Family",
        "members": 4,
        "methodOfInvitation": "Phone"
    },
    {
        "name": "Angela Family",
        "members": 5,
        "methodOfInvitation": "Phone"
    },
    {
        "name": "Julius Family",
        "members": 3,
        "methodOfInvitation": "Phone"
    },
    {
        "name": "Maxwell Family",
        "members": 2,
        "methodOfInvitation": "Phone"
    },
    {
        "name": "Offiong Family",
        "members": 1,
        "methodOfInvitation": "Phone"
    },
    {
        "name": "Nwankwor Family",
        "members": 4,
        "methodOfInvitation": "Phone"
    },
    {
        "name": "Nwachukwu Family",
        "members": 6,
        "methodOfInvitation": "Phone"
    },
    {
        "name": "Chinedu Family",
        "members": 7,
        "methodOfInvitation": "Phone"
    },
    {
        "name": "Ogra Family",
        "members": 3,
        "methodOfInvitation": "Phone"
    },
    {
        "name": "Tudonu Family",
        "members": 2,
        "methodOfInvitation": "Card"
    },
    {
        "name": "Oboravo Family",
        "members": 2,
        "methodOfInvitation": "Card"
    },
    {
        "name": "Akpan Family",
        "members": 2,
        "methodOfInvitation": "Phone"
    },
    {
        "name": "Akaolisa Family",
        "members": 2,
        "methodOfInvitation": "Phone"
    },
    {
        "name": "Ojo Family",
        "members": 2,
        "methodOfInvitation": "Phone"
    },
    {
        "name": "Sis Okoro",
        "members": 1,
        "methodOfInvitation": "Card"
    },
    {
        "name": "Omiunu Family",
        "members": 2,
        "methodOfInvitation": "Card"
    },
    {
        "name": "Azubuike Family",
        "members": 2,
        "methodOfInvitation": "Phone"
    },
    {
        "name": "Aaron Family",
        "members": 2,
        "methodOfInvitation": "Phone"
    },
    {
        "name": "Anidu Family",
        "members": 2,
        "methodOfInvitation": "Phone"
    },
    {
        "name": "Effiong Family",
        "members": 2,
        "methodOfInvitation": "Card"
    },
    {
        "name": "Daniel Ohioma Family",
        "members": 2,
        "methodOfInvitation": "Phone"
    },
    {
        "name": "Sis Anyanwu Christiana",
        "members": 3,
        "methodOfInvitation": "Phone"
    },
    {
        "name": "Daddy Vivian",
        "members": 1,
        "methodOfInvitation": "Card"
    },
    {
        "name": "Gospel Family",
        "members": 2,
        "methodOfInvitation": "Card"
    },
    {
        "name": "Nwaodu Family",
        "members": 2,
        "methodOfInvitation": "Card"
    },
    {
        "name": "Okereke Family",
        "members": 2,
        "methodOfInvitation": "Card"
    },
    {
        "name": "Ekeh Family",
        "members": 2,
        "methodOfInvitation": "Phone"
    },
    {
        "name": "Abalaba Family",
        "members": 3,
        "methodOfInvitation": "Phone"
    },
    {
        "name": "Egwuogu Family",
        "members": 2,
        "methodOfInvitation": "Phone"
    },
    {
        "name": "Sis Iheme",
        "members": 1,
        "methodOfInvitation": "Card"
    },
    {
        "name": "Kelvin Family",
        "members": 5,
        "methodOfInvitation": "Card"
    },
    {
        "name": "Baagry Family",
        "members": 2,
        "methodOfInvitation": "Card"
    },
    {
        "name": "Awa Family",
        "members": 2,
        "methodOfInvitation": "Card"
    }
]